docspace_api_sdk/__init__.py
docspace_api_sdk/api/__init__.py
docspace_api_sdk/api/api_keys/api_keys_api.py
docspace_api_sdk/api/authentication/authentication_api.py
docspace_api_sdk/api/backup/backup_api.py
docspace_api_sdk/api/capabilities/capabilities_api.py
docspace_api_sdk/api/files/files_api.py
docspace_api_sdk/api/files/folders_api.py
docspace_api_sdk/api/files/operations_api.py
docspace_api_sdk/api/files/quota_api.py
docspace_api_sdk/api/files/settings_api.py
docspace_api_sdk/api/files/sharing_api.py
docspace_api_sdk/api/files/third_party_integration_api.py
docspace_api_sdk/api/group/group_api.py
docspace_api_sdk/api/group/search_api.py
docspace_api_sdk/api/migration/migration_api.py
docspace_api_sdk/api/o_auth20/authorization_api.py
docspace_api_sdk/api/o_auth20/client_management_api.py
docspace_api_sdk/api/o_auth20/client_querying_api.py
docspace_api_sdk/api/o_auth20/scope_management_api.py
docspace_api_sdk/api/people/guests_api.py
docspace_api_sdk/api/people/password_api.py
docspace_api_sdk/api/people/photos_api.py
docspace_api_sdk/api/people/profiles_api.py
docspace_api_sdk/api/people/quota_api.py
docspace_api_sdk/api/people/search_api.py
docspace_api_sdk/api/people/theme_api.py
docspace_api_sdk/api/people/third_party_accounts_api.py
docspace_api_sdk/api/people/user_data_api.py
docspace_api_sdk/api/people/user_status_api.py
docspace_api_sdk/api/people/user_type_api.py
docspace_api_sdk/api/portal/guests_api.py
docspace_api_sdk/api/portal/payment_api.py
docspace_api_sdk/api/portal/quota_api.py
docspace_api_sdk/api/portal/settings_api.py
docspace_api_sdk/api/portal/users_api.py
docspace_api_sdk/api/rooms/rooms_api.py
docspace_api_sdk/api/security/access_to_dev_tools_api.py
docspace_api_sdk/api/security/active_connections_api.py
docspace_api_sdk/api/security/audit_trail_data_api.py
docspace_api_sdk/api/security/banners_visibility_api.py
docspace_api_sdk/api/security/csp_api.py
docspace_api_sdk/api/security/firebase_api.py
docspace_api_sdk-3.5.1.dist-info/METADATA
docspace_api_sdk-3.5.1.dist-info/WHEEL
docspace_api_sdk-3.5.1.dist-info/licenses/AUTHORS.md
docspace_api_sdk-3.5.1.dist-info/licenses/LICENSE
docspace_api_sdk-3.5.1.dist-info/RECORD
