Metadata-Version: 2.4
Name: docspace_api_sdk
Version: 3.5.1
Summary: A simple Python SDK for integrating with the ONLYOFFICE DocSpace API
License: Apache-2.0
License-File: AUTHORS.md
License-File: LICENSE
Keywords: onlyoffice,docspace,sdk
Author: Ascensio System SIA
Author-email: integration@onlyoffice.com
Requires-Python: >=3.9,<4.0
Classifier: License :: OSI Approved :: Apache Software License
Classifier: Programming Language :: Python :: 3
Classifier: Programming Language :: Python :: 3.9
Classifier: Programming Language :: Python :: 3.10
Classifier: Programming Language :: Python :: 3.11
Classifier: Programming Language :: Python :: 3.12
Classifier: Programming Language :: Python :: 3.13
Classifier: Programming Language :: Python :: 3.14
Requires-Dist: pydantic (>=2)
Requires-Dist: python-dateutil (>=2.8.2)
Requires-Dist: typing-extensions (>=4.7.1)
Requires-Dist: urllib3 (>=2.1.0,<3.0.0)
Project-URL: Homepage, https://www.onlyoffice.com
Project-URL: Repository, https://github.com/ONLYOFFICE/docspace-api-sdk-python
